[
  {
    "id": "3d47aef0-b26a-5eb2-937f-360c2f0d6d0d",
    "name": "Barnegat High School",
    "type": "School",
    "address": "180 Bengal Blvd, Barnegat, NJ 08005",
    "county": "Ocean",
    "source": "nj_schools_public",
    "confidence": "high"
  },
  {
    "id": "9a10f911-13f4-5485-bca1-634349f5311d",
    "name": "Cecil S. Collins Elementary",
    "type": "School",
    "address": "570 Barnegat Blvd North, Barnegat, NJ 08005",
    "county": "Ocean",
    "source": "nj_schools_public",
    "confidence": "high"
  },
  {
    "id": "4e513753-f69c-5be4-84ac-17c5910068f4",
    "name": "Joseph T. Donahue Elementary School",
    "type": "School",
    "address": "200 Bengal Blvd, Barnegat, NJ 08005",
    "county": "Ocean",
    "source": "nj_schools_public",
    "confidence": "high"
  },
  {
    "id": "24c16488-1798-5996-a6c9-c8c1b514712d",
    "name": "Lillian M. Dunfee Elementary",
    "type": "School",
    "address": "128 Barnegat Blvd, Barnegat, NJ 08005-2497",
    "county": "Ocean",
    "source": "nj_schools_public",
    "confidence": "high"
  },
  {
    "id": "e8a0252f-ff79-5240-a247-6f442caceccf",
    "name": "Robert L. Horbelt Elementary School",
    "type": "School",
    "address": "104 Burr Street, Barnegat, NJ 08005",
    "county": "Ocean",
    "source": "nj_schools_public",
    "confidence": "high"
  },
  {
    "id": "c099bac8-97a9-52bf-ac15-20d91f057268",
    "name": "Russell O. Brackman Middle School",
    "type": "School",
    "address": "600 Barnegat Blvd North, Barnegat, NJ 08005",
    "county": "Ocean",
    "source": "nj_schools_public",
    "confidence": "high"
  },
  {
    "id": "03da2baf-f7a1-58ea-bc88-584689832df4",
    "name": "Bay Head Elementary",
    "type": "School",
    "address": "145 Grove Street, Bay Head, NJ 08742",
    "county": "Ocean",
    "source": "nj_schools_public",
    "confidence": "high"
  },
  {
    "id": "aa946442-73a3-5667-8491-a81ec8384940",
    "name": "Beach Haven School",
    "type": "School",
    "address": "700 North Beach Ave., Beach Haven, NJ 08008",
    "county": "Ocean",
    "source": "nj_schools_public",
    "confidence": "high"
  },
  {
    "id": "d6575cf2-72e4-564f-98e2-a436c8e91d82",
    "name": "Bayville Elementary School",
    "type": "School",
    "address": "356 Atlantic City Blvd, Bayville, NJ 08721-1246",
    "county": "Ocean",
    "source": "nj_schools_public",
    "confidence": "high"
  },
  {
    "id": "bda392aa-1639-570b-87bf-4d1098eb253c",
    "name": "Berkeley Township Elementary School",
    "type": "School",
    "address": "10 Emory Avenue, Bayville, NJ 08721",
    "county": "Ocean",
    "source": "nj_schools_public",
    "confidence": "high"
  },
  {
    "id": "48adf4ed-04f2-5b0a-90ec-ca11006dd0b7",
    "name": "Clara B. Worth Elementary School",
    "type": "School",
    "address": "57 Central Parkway, Bayville, NJ 08721-2414",
    "county": "Ocean",
    "source": "nj_schools_public",
    "confidence": "high"
  },
  {
    "id": "a3cd7d1a-786b-56fa-9840-e8a806dfb6cf",
    "name": "H & M Potter School",
    "type": "School",
    "address": "60 Veeder Lane, Bayville, NJ 08721-1833",
    "county": "Ocean",
    "source": "nj_schools_public",
    "confidence": "high"
  },
  {
    "id": "986d8afc-ef23-5ab2-9078-f466bd372196",
    "name": "Brick Township High School",
    "type": "School",
    "address": "346 Chambers Bridge Rd, Brick Town, NJ 08723-2804",
    "county": "Ocean",
    "source": "nj_schools_public",
    "confidence": "high"
  },
  {
    "id": "ae52b1b3-ceb5-5131-9379-a668991daa71",
    "name": "Brick Township Memorial High School",
    "type": "School",
    "address": "2001 Lanes Mill Rd, Brick, NJ 08724-1405",
    "county": "Ocean",
    "source": "nj_schools_public",
    "confidence": "high"
  },
  {
    "id": "16ad0bf5-272f-50ef-95c8-084193d48c23",
    "name": "Drum Point Road Elementary School",
    "type": "School",
    "address": "41 Drum Point Rd, Brick Town, NJ 08723-6021",
    "county": "Ocean",
    "source": "nj_schools_public",
    "confidence": "high"
  },
  {
    "id": "b540a360-04cd-5bfa-a7ad-821d3708b52a",
    "name": "Emma Havens Young Elementary School",
    "type": "School",
    "address": "43 Drum Point Rd, Brick, NJ 08723-6021",
    "county": "Ocean",
    "source": "nj_schools_public",
    "confidence": "high"
  },
  {
    "id": "db778c8c-7a16-5966-b1aa-b5ab4c5c7f7d",
    "name": "Herbertsville Early Childhood Development Center",
    "type": "School",
    "address": "2282 Lanes Mill Rd, Brick, NJ 08724-1003",
    "county": "Ocean",
    "source": "nj_schools_public",
    "confidence": "high"
  },
  {
    "id": "ee3ea0ae-457f-5120-ac8d-9b6ed4d8eb8d",
    "name": "Lake Riviera Middle School",
    "type": "School",
    "address": "171 Beaverson Boulevard, Brick, NJ 08723",
    "county": "Ocean",
    "source": "nj_schools_public",
    "confidence": "high"
  },
  {
    "id": "10e91231-86de-58c7-b9d7-a9ff2997cfe3",
    "name": "Lanes Mill Elementary School",
    "type": "School",
    "address": "1891 Lanes Mill Rd, Brick, NJ 08724-1445",
    "county": "Ocean",
    "source": "nj_schools_public",
    "confidence": "high"
  },
  {
    "id": "88190766-4e7d-5cbd-9915-e486c3e9ba97",
    "name": "Midstreams Elementary School",
    "type": "School",
    "address": "500 Midstreams Rd, Brick Town, NJ 08724-3816",
    "county": "Ocean",
    "source": "nj_schools_public",
    "confidence": "high"
  },
  {
    "id": "64b42f40-165d-5cb9-8788-24455bcaf3f0",
    "name": "Osbornville Elementary School",
    "type": "School",
    "address": "218 Drum Point Rd, Brick, NJ 08723-6312",
    "county": "Ocean",
    "source": "nj_schools_public",
    "confidence": "high"
  },
  {
    "id": "b8ec7dfd-31a2-552d-b6e4-50431e0ee11a",
    "name": "Veterans Memorial Elementary School",
    "type": "School",
    "address": "103 Hendrickson Avenue, Brick, NJ 08724",
    "county": "Ocean",
    "source": "nj_schools_public",
    "confidence": "high"
  },
  {
    "id": "43da0ae4-874f-5fb8-8c9f-f603548e5064",
    "name": "Veterans Memorial Middle School",
    "type": "School",
    "address": "105 Hendrickson Avenue, Brick Town, NJ 08724",
    "county": "Ocean",
    "source": "nj_schools_public",
    "confidence": "high"
  },
  {
    "id": "d1faa932-1cdf-51ce-9a7e-63c31080a1a1",
    "name": "Warren H. Wolf Early Childhood Development Center",
    "type": "School",
    "address": "224 Chambers Bridge Rd, Brick, NJ 08723-9999",
    "county": "Ocean",
    "source": "nj_schools_public",
    "confidence": "high"
  },
  {
    "id": "8f70a78a-6522-5a64-a64d-470cb9a09ddd",
    "name": "Central Regional High School",
    "type": "School",
    "address": "509 Forest Hills Parkway, Bayville, NJ 08721",
    "county": "Ocean",
    "source": "nj_schools_public",
    "confidence": "high"
  },
  {
    "id": "92b485fc-4c2c-5950-accb-54aac90bf108",
    "name": "Central Regional Middle School",
    "type": "School",
    "address": "509 Forest Hills Parkway, Bayville, NJ 08721",
    "county": "Ocean",
    "source": "nj_schools_public",
    "confidence": "high"
  },
  {
    "id": "298aba3a-6bb7-5941-b451-35c8814d7689",
    "name": "Eagleswood Elementary School",
    "type": "School",
    "address": "511 Route 9, West Creek, NJ 08092",
    "county": "Ocean",
    "source": "nj_schools_public",
    "confidence": "high"
  },
  {
    "id": "56e71c70-a470-59db-9d82-3c5c60cb6df2",
    "name": "Island Heights Elementary School",
    "type": "School",
    "address": "115 Summit Ave, Po Box 329, Island Heights, NJ 08732-0329",
    "county": "Ocean",
    "source": "nj_schools_public",
    "confidence": "high"
  },
  {
    "id": "2e871684-2186-5bc9-b269-47478777d4b1",
    "name": "Crawford - Rodriguez Elementary School",
    "type": "School",
    "address": "1025 Larsen Road, Jackson, NJ 08527-3497",
    "county": "Ocean",
    "source": "nj_schools_public",
    "confidence": "high"
  },
  {
    "id": "aa7eba69-37b5-5739-9ad0-811445aca294",
    "name": "Elms Elementary School",
    "type": "School",
    "address": "780 Patterson Road, Jackson, NJ 08527-3497",
    "county": "Ocean",
    "source": "nj_schools_public",
    "confidence": "high"
  },
  {
    "id": "fc5b094a-d1f5-57bf-af9b-9d9938fa5e6e",
    "name": "Howard C. Johnson Elementary School",
    "type": "School",
    "address": "1021 Larsen Road, Jackson, NJ 08527-3497",
    "county": "Ocean",
    "source": "nj_schools_public",
    "confidence": "high"
  },
  {
    "id": "7b151528-d23b-5e4f-8dde-b55ab849d8d6",
    "name": "Jackson Township 5 - 6 School",
    "type": "School",
    "address": "835 Patterson Road, Jackson, NJ 08527-3497",
    "county": "Ocean",
    "source": "nj_schools_public",
    "confidence": "high"
  },
  {
    "id": "c88d1029-5a23-55b3-a8d6-838da6d84eea",
    "name": "Jackson Township High School",
    "type": "School",
    "address": "125 North Hope Chapel Road, Jackson, NJ 08527-3497",
    "county": "Ocean",
    "source": "nj_schools_public",
    "confidence": "high"
  },
  {
    "id": "6b167738-5392-550a-a988-bac642fbdd8c",
    "name": "Jackson Township Middle School",
    "type": "School",
    "address": "101 Don Connor Blvd, Jackson, NJ 08527-3497",
    "county": "Ocean",
    "source": "nj_schools_public",
    "confidence": "high"
  },
  {
    "id": "3aaf5dc0-412a-521b-9c00-d763f8c7b69d",
    "name": "Lucy N. Holman Elementary School",
    "type": "School",
    "address": "125 Manhattan Street, Jackson, NJ 08527-3497",
    "county": "Ocean",
    "source": "nj_schools_public",
    "confidence": "high"
  },
  {
    "id": "f22ee9c4-80dc-59c8-9e29-bb32ec274612",
    "name": "Switlik Elementary School",
    "type": "School",
    "address": "75 West Veterans Highway, Jackson, NJ 08527-3497",
    "county": "Ocean",
    "source": "nj_schools_public",
    "confidence": "high"
  },
  {
    "id": "8f31c7d7-aa82-5ed5-a3ed-90bff75f4bfa",
    "name": "Cedar Creek Elementary School",
    "type": "School",
    "address": "220 Western Blvd, Lanoka Harbor, NJ 08734-0313",
    "county": "Ocean",
    "source": "nj_schools_public",
    "confidence": "high"
  },
  {
    "id": "340468f1-55c4-57d3-8c5e-11b6e7490d5f",
    "name": "Forked River Elementary School",
    "type": "School",
    "address": "110 Lacey Road, Forked River, NJ 08731-0477",
    "county": "Ocean",
    "source": "nj_schools_public",
    "confidence": "high"
  },
  {
    "id": "472aac27-b156-51c9-b9c2-22be05903aac",
    "name": "Lacey Township High School",
    "type": "School",
    "address": "73 Haines Street, Lanoka Harbor, NJ 08734",
    "county": "Ocean",
    "source": "nj_schools_public",
    "confidence": "high"
  },
  {
    "id": "6ae1f959-b6a1-5af9-9b58-daa583350e5e",
    "name": "Lacey Township Middle School",
    "type": "School",
    "address": "660 Denton Avenue, Forked River, NJ 08731-0535",
    "county": "Ocean",
    "source": "nj_schools_public",
    "confidence": "high"
  },
  {
    "id": "734b4871-6ee2-50c0-a1d7-ae2ae22a54e9",
    "name": "Lanoka Harbor Elementary School",
    "type": "School",
    "address": "281 Manchester Ave, Lanoka Harbor, NJ 08734",
    "county": "Ocean",
    "source": "nj_schools_public",
    "confidence": "high"
  },
  {
    "id": "5be9ec09-2546-5c44-bd91-3aa64b439c22",
    "name": "Mill Pond Elementary School",
    "type": "School",
    "address": "210 Western Blvd, Lanoka Harbor, NJ 08734",
    "county": "Ocean",
    "source": "nj_schools_public",
    "confidence": "high"
  },
  {
    "id": "b4ab6783-48e3-59dd-8d34-68c7936afd9b",
    "name": "Lakehurst Elementary School",
    "type": "School",
    "address": "301 Union Ave, Lakehurst, NJ 08733-2935",
    "county": "Ocean",
    "source": "nj_schools_public",
    "confidence": "high"
  },
  {
    "id": "8e963d7b-80c2-5de3-935d-4975f3f0512c",
    "name": "Clifton Ave Grade School",
    "type": "School",
    "address": "625 Clifton Avenue, Lakewood, NJ 08701",
    "county": "Ocean",
    "source": "nj_schools_public",
    "confidence": "high"
  },
  {
    "id": "afd204af-5650-5855-aa4f-2f47c8764a1a",
    "name": "Lakewood Adult High School",
    "type": "School",
    "address": "855 Somerset Avenue, Lakewood, NJ 08701",
    "county": "Ocean",
    "source": "nj_schools_public",
    "confidence": "high"
  },
  {
    "id": "f6677f16-c773-5b67-b2f0-c02aabec3358",
    "name": "Lakewood High School",
    "type": "School",
    "address": "855 Somerset Avenue, Lakewood, NJ 08701",
    "county": "Ocean",
    "source": "nj_schools_public",
    "confidence": "high"
  },
  {
    "id": "7d53c3df-02cf-5e1f-97b9-0380b8994c6e",
    "name": "Lakewood Middle School",
    "type": "School",
    "address": "755 Somerset Avenue, Lakewood, NJ 08701",
    "county": "Ocean",
    "source": "nj_schools_public",
    "confidence": "high"
  },
  {
    "id": "ad16a6fa-4a3a-5e4a-8ae6-5a5d7b36ee45",
    "name": "Oak Street Elem School",
    "type": "School",
    "address": "75 Oak Street, Lakewood, NJ 08701",
    "county": "Ocean",
    "source": "nj_schools_public",
    "confidence": "high"
  },
  {
    "id": "7309aefa-c9ea-5145-8907-cf98d529946d",
    "name": "Spruce Street Elementary School",
    "type": "School",
    "address": "90 Spruce Street, Lakewood, NJ 08701",
    "county": "Ocean",
    "source": "nj_schools_public",
    "confidence": "high"
  },
  {
    "id": "7ebdade4-7cf7-5477-a7a0-0ff61458b4da",
    "name": "Lavallette Elementary School",
    "type": "School",
    "address": "105 Brooklyn Ave., Lavallette, NJ 08735-2321",
    "county": "Ocean",
    "source": "nj_schools_public",
    "confidence": "high"
  },
  {
    "id": "4666be43-5af5-5286-b369-30f11e8fbf9f",
    "name": "Frog Pond Elementary School",
    "type": "School",
    "address": "305 Frog Pond Road, Little Egg Harbor, NJ 08087",
    "county": "Ocean",
    "source": "nj_schools_public",
    "confidence": "high"
  },
  {
    "id": "6bf12bcf-ba74-52ed-8a8e-318e7569c9d1",
    "name": "George J. Mitchell Elementary School",
    "type": "School",
    "address": "950 Route 539, Little Egg Harbor, NJ 08087-9750",
    "county": "Ocean",
    "source": "nj_schools_public",
    "confidence": "high"
  },
  {
    "id": "a39eabba-9fbf-5d9b-949f-91cc3861d811",
    "name": "Robert C. Wood Sr Early Childhood Center",
    "type": "School",
    "address": "950 Route 539, Little Egg Harbor, NJ 08087",
    "county": "Ocean",
    "source": "nj_schools_public",
    "confidence": "high"
  },
  {
    "id": "079f16c7-9b50-5d19-bb8f-0806c106486c",
    "name": "Long Beach Island Elementary School",
    "type": "School",
    "address": "200 S. Barnegat Avenue, Surf City, NJ 08008",
    "county": "Ocean",
    "source": "nj_schools_public",
    "confidence": "high"
  },
  {
    "id": "d585515e-52dd-5013-b11c-3829d70e0c08",
    "name": "Manchester Regional Day School",
    "type": "School",
    "address": "890 Toms River Road, Jackson, NJ 08527-9105",
    "county": "Ocean",
    "source": "nj_schools_public",
    "confidence": "high"
  },
  {
    "id": "95b8d0aa-1e61-5a6b-9b5a-6b8f150b7196",
    "name": "Manchester Township Elementary School",
    "type": "School",
    "address": "101 N Colonial Drive, Manchester, NJ 08733",
    "county": "Ocean",
    "source": "nj_schools_public",
    "confidence": "high"
  },
  {
    "id": "83059d58-3a05-5e6c-983c-7e2082dcc0b1",
    "name": "Manchester Township High School",
    "type": "School",
    "address": "101 Hawks Way, Manchester, NJ 08759",
    "county": "Ocean",
    "source": "nj_schools_public",
    "confidence": "high"
  },
  {
    "id": "dd3e7caf-c8f5-5e7f-b638-25d611e072b7",
    "name": "Manchester Township Middle School",
    "type": "School",
    "address": "2759 Ridgeway Rd, Manchester, NJ 08759",
    "county": "Ocean",
    "source": "nj_schools_public",
    "confidence": "high"
  },
  {
    "id": "ea867927-f2a4-53bf-ab1e-594d826fc921",
    "name": "Ridgeway Elementary School",
    "type": "School",
    "address": "2861 Ridgeway Rd, Manchester, NJ 08759",
    "county": "Ocean",
    "source": "nj_schools_public",
    "confidence": "high"
  },
  {
    "id": "c5b17fd7-73b0-5b95-80e1-4cfb528686cc",
    "name": "Whiting Elementary School",
    "type": "School",
    "address": "412 Manchester Blvd, Whiting, NJ 08759-1336",
    "county": "Ocean",
    "source": "nj_schools_public",
    "confidence": "high"
  },
  {
    "id": "e5841419-01fe-5614-bfb9-202c0170a44b",
    "name": "Marine Academy Of Technology And Environmental Science",
    "type": "School",
    "address": "195 Cedar Bridge Road, Manahawkin, NJ 08050",
    "county": "Ocean",
    "source": "nj_schools_public",
    "confidence": "high"
  },
  {
    "id": "ef8e39f5-ce81-520d-a33d-a03efde70403",
    "name": "Ocvts Grunin Performing Arts Academy",
    "type": "School",
    "address": "1 College Drive, Bldg. #12, Toms River, NJ 08754",
    "county": "Ocean",
    "source": "nj_schools_public",
    "confidence": "high"
  },
  {
    "id": "a5f1e5a1-cc3a-5ac0-9789-b54e8a19c5d9",
    "name": "Ocean County Vocational Technical School Brick Center",
    "type": "School",
    "address": "350 Chambers Bridge Road, Brick, NJ 08723-2896",
    "county": "Ocean",
    "source": "nj_schools_public",
    "confidence": "high"
  },
  {
    "id": "16534c54-bc31-5c6c-81a4-8e5576e0ee25",
    "name": "Ocean County Vocational Technical School Culinary Center",
    "type": "School",
    "address": "261 Country Club Blvd., Little Egg Harbor, NJ 08087",
    "county": "Ocean",
    "source": "nj_schools_public",
    "confidence": "high"
  },
  {
    "id": "27223cdc-b874-5de0-ab9d-79e79120663c",
    "name": "Ocean County Vocational Technical School Jackson Center",
    "type": "School",
    "address": "850 Toms River Road, Jackson, NJ 08527-9241",
    "county": "Ocean",
    "source": "nj_schools_public",
    "confidence": "high"
  },
  {
    "id": "544c841e-e4ce-5b22-8611-9e63a08b5ac1",
    "name": "Ocean County Vocational Technical School Toms River Center",
    "type": "School",
    "address": "1299 Old Freehold Road, Toms River, NJ 08753-4298",
    "county": "Ocean",
    "source": "nj_schools_public",
    "confidence": "high"
  },
  {
    "id": "3e7b91ac-ced3-56f3-90c3-e862825fb9fe",
    "name": "Ocean County Vocational Technical School Waretown Center",
    "type": "School",
    "address": "1 College Drive, Building #7, Toms River, NJ 08754",
    "county": "Ocean",
    "source": "nj_schools_public",
    "confidence": "high"
  },
  {
    "id": "6ea642f2-d319-544d-9238-fb09b87420b2",
    "name": "Ocean County Vocational And Technical Schools Waretown",
    "type": "School",
    "address": "423 Wells Mills Rd, Waretown, NJ 08758",
    "county": "Ocean",
    "source": "nj_schools_public",
    "confidence": "high"
  },
  {
    "id": "39a55626-0bb2-51d5-8cb5-4ab1ecc60bda",
    "name": "Ocean Gate Elementary School",
    "type": "School",
    "address": "126 West Arverne Avenue, Po Box 478, Ocean Gate, NJ 08740-0478",
    "county": "Ocean",
    "source": "nj_schools_public",
    "confidence": "high"
  },
  {
    "id": "d1a35b07-1ea3-5634-ae0d-e0fdb20e2f41",
    "name": "Frederic A. Priff Elementary School",
    "type": "School",
    "address": "139 Wells Mill Road, Waretown, NJ 08758-2606",
    "county": "Ocean",
    "source": "nj_schools_public",
    "confidence": "high"
  },
  {
    "id": "1ec96f34-a814-5e16-ad8b-0ef9e08eb095",
    "name": "Waretown Elementary School",
    "type": "School",
    "address": "64 Railroad Avenue, Waretown, NJ 08758-2717",
    "county": "Ocean",
    "source": "nj_schools_public",
    "confidence": "high"
  },
  {
    "id": "de615c0a-b58c-5ed5-9d9e-5bc041d9ffad",
    "name": "Pinelands Regional High School",
    "type": "School",
    "address": "565 Nugentown Road, Little Egg Harbor, NJ 08087-0248",
    "county": "Ocean",
    "source": "nj_schools_public",
    "confidence": "high"
  },
  {
    "id": "2c4a1b39-325b-5468-8d45-b851ab1cc172",
    "name": "Pinelands Regional Jr. High School",
    "type": "School",
    "address": "590 Nugentown Road, Little Egg Harbor, NJ 08087-0248",
    "county": "Ocean",
    "source": "nj_schools_public",
    "confidence": "high"
  },
  {
    "id": "912ac424-f8d8-5b98-b579-4ebf9eb412b9",
    "name": "Dr. Gerald H. Woehr Elementary School",
    "type": "School",
    "address": "44 N Main St, New Egypt, NJ 08533-1316",
    "county": "Ocean",
    "source": "nj_schools_public",
    "confidence": "high"
  },
  {
    "id": "762f7099-435c-5c6f-9e05-f162ae2b3605",
    "name": "New Egypt High School",
    "type": "School",
    "address": "117 Evergreen Road, New Egypt, NJ 08533-1316",
    "county": "Ocean",
    "source": "nj_schools_public",
    "confidence": "high"
  },
  {
    "id": "71a4578b-9828-5a03-9a60-725c4a8871ab",
    "name": "New Egypt Primary School",
    "type": "School",
    "address": "131 Evergreen Road, New Egypt, NJ 08533",
    "county": "Ocean",
    "source": "nj_schools_public",
    "confidence": "high"
  },
  {
    "id": "90d26ad7-038e-5b51-8e53-84c1ee275bfa",
    "name": "G. Harold Antrim Elementary School",
    "type": "School",
    "address": "401 Niblick Street, Point Pleasant Beach, NJ 08742",
    "county": "Ocean",
    "source": "nj_schools_public",
    "confidence": "high"
  },
  {
    "id": "fd63b1ea-1383-5a0d-937a-ab6a8d6eb4a2",
    "name": "Point Pleasant Beach High School",
    "type": "School",
    "address": "700 Trenton Avenue, Point Pleasant Beach, NJ 08742",
    "county": "Ocean",
    "source": "nj_schools_public",
    "confidence": "high"
  },
  {
    "id": "a2f90761-8532-59d1-a7cd-e129ca04f069",
    "name": "Memorial Middle School",
    "type": "School",
    "address": "808 Laura Herbert Dr, Point Pleasant, NJ 08742",
    "county": "Ocean",
    "source": "nj_schools_public",
    "confidence": "high"
  },
  {
    "id": "2cef9612-0dae-5599-bf2b-0fe1a96dbccb",
    "name": "Nellie F. Bennett Elementary School",
    "type": "School",
    "address": "2000 Riviera Parkway, Point Pleasant, NJ 08742",
    "county": "Ocean",
    "source": "nj_schools_public",
    "confidence": "high"
  },
  {
    "id": "c5ca5eb3-0dfe-55ea-a796-d398e2cd4061",
    "name": "Ocean Road Elementary School",
    "type": "School",
    "address": "1210 Benedict Street, Point Pleasant, NJ 08742",
    "county": "Ocean",
    "source": "nj_schools_public",
    "confidence": "high"
  },
  {
    "id": "416ce3b3-500a-50fe-b090-39298ee6d769",
    "name": "Point Pleasant Borough High School",
    "type": "School",
    "address": "830 Laura Herbert Dr, Point Pleasant, NJ 08742",
    "county": "Ocean",
    "source": "nj_schools_public",
    "confidence": "high"
  },
  {
    "id": "72b37f46-0a89-5770-9b1d-03781e1d66b4",
    "name": "Hugh J. Boyd Jr. Elementary School",
    "type": "School",
    "address": "1200 Bay Boulevard, Seaside Hts, NJ 08751",
    "county": "Ocean",
    "source": "nj_schools_public",
    "confidence": "high"
  },
  {
    "id": "aecb8a44-9e70-57ae-8b12-c82fb7983b07",
    "name": "Southern Regional High School",
    "type": "School",
    "address": "90 Cedar Bridge Road, Manahawkin, NJ 08050-3022",
    "county": "Ocean",
    "source": "nj_schools_public",
    "confidence": "high"
  },
  {
    "id": "a8e4729f-260f-5c33-9b11-fce3ec8a2f49",
    "name": "Southern Regional Middle School",
    "type": "School",
    "address": "75 Cedar Bridge Road, Manahawkin, NJ 08050-3056",
    "county": "Ocean",
    "source": "nj_schools_public",
    "confidence": "high"
  },
  {
    "id": "78c83495-5479-5849-a2d4-b7ce89bff9f6",
    "name": "Mckinley Avenue Elementary School",
    "type": "School",
    "address": "1000 Mckinley Avenue, Manahawkin, NJ 08050-2807",
    "county": "Ocean",
    "source": "nj_schools_public",
    "confidence": "high"
  },
  {
    "id": "c3e16923-9c61-52e8-bd45-feca102de961",
    "name": "Ocean Acres Elementary School",
    "type": "School",
    "address": "489 Nautilus Drive, Manahawkin, NJ 08050",
    "county": "Ocean",
    "source": "nj_schools_public",
    "confidence": "high"
  },
  {
    "id": "90737ff1-ed0f-5a20-aea2-13f71c7a4a77",
    "name": "Oxycocus Elementary School",
    "type": "School",
    "address": "250 North Main Street, Manahawkin, NJ 08050-3011",
    "county": "Ocean",
    "source": "nj_schools_public",
    "confidence": "high"
  },
  {
    "id": "b6092691-597a-5ecb-931f-d442ad53805c",
    "name": "Ronald L. Meinders Primary Learning Center",
    "type": "School",
    "address": "1000 Mckinley Avenue, Manahawkin, NJ 08050",
    "county": "Ocean",
    "source": "nj_schools_public",
    "confidence": "high"
  },
  {
    "id": "bd15ca26-0006-5459-86d3-18edaef1f396",
    "name": "Stafford Intermediate School",
    "type": "School",
    "address": "1000 Mckinley Avenue, Manahawkin, NJ 08050",
    "county": "Ocean",
    "source": "nj_schools_public",
    "confidence": "high"
  },
  {
    "id": "fa593d1f-eb16-57f3-b3e1-7b52b2e23878",
    "name": "Beachwood Elementary School",
    "type": "School",
    "address": "901 Berkeley Avenue, Beachwood, NJ 08722",
    "county": "Ocean",
    "source": "nj_schools_public",
    "confidence": "high"
  },
  {
    "id": "8bc44739-0f8f-5be7-b1f8-af2cbdd08786",
    "name": "Cedar Grove Elementary School",
    "type": "School",
    "address": "179 Cedar Grove Road, Toms River, NJ 08753-4399",
    "county": "Ocean",
    "source": "nj_schools_public",
    "confidence": "high"
  },
  {
    "id": "e8a8bfdb-9dbd-5893-bb47-0a5daf2347e1",
    "name": "East Dover Elementary School",
    "type": "School",
    "address": "725 Vaughn Avenue, Toms River, NJ 08753",
    "county": "Ocean",
    "source": "nj_schools_public",
    "confidence": "high"
  },
  {
    "id": "05476d2e-03a8-579c-8d62-9d90e3c4a843",
    "name": "Hooper Avenue Elementary School",
    "type": "School",
    "address": "1517 Hooper Avenue, Toms River, NJ 08753",
    "county": "Ocean",
    "source": "nj_schools_public",
    "confidence": "high"
  },
  {
    "id": "f13ce94e-820c-557e-bd10-8882fa4551b2",
    "name": "Joseph A. Citta Elementary School",
    "type": "School",
    "address": "2050 Lakewood Road, Toms River, NJ 08755",
    "county": "Ocean",
    "source": "nj_schools_public",
    "confidence": "high"
  },
  {
    "id": "0a773974-8c62-5ec3-87b1-ee5b453a13e1",
    "name": "North Dover Elementary School",
    "type": "School",
    "address": "1759 New Hampshire Avenue, Toms River, NJ 08753",
    "county": "Ocean",
    "source": "nj_schools_public",
    "confidence": "high"
  },
  {
    "id": "46803dfc-495a-549c-8d49-f4301d1d4aab",
    "name": "Pine Beach Elementary School",
    "type": "School",
    "address": "101 Pennsylvania Avenue, Pine Beach, NJ 08741",
    "county": "Ocean",
    "source": "nj_schools_public",
    "confidence": "high"
  },
  {
    "id": "5a55fc8a-96a5-5521-8de7-2532e9cc6b08",
    "name": "Silver Bay Elementary School",
    "type": "School",
    "address": "100 Silver Bay Road, Toms River, NJ 08753",
    "county": "Ocean",
    "source": "nj_schools_public",
    "confidence": "high"
  },
  {
    "id": "124f8569-9da9-56be-afe2-96b1f7544b50",
    "name": "South Toms River Elementary School",
    "type": "School",
    "address": "419 Dover Road, South Toms River, NJ 08757",
    "county": "Ocean",
    "source": "nj_schools_public",
    "confidence": "high"
  },
  {
    "id": "ba084803-b2ea-511e-8f3e-551119eb20a3",
    "name": "Toms River High School East",
    "type": "School",
    "address": "1225 Raider Way, Toms River, NJ 08753",
    "county": "Ocean",
    "source": "nj_schools_public",
    "confidence": "high"
  },
  {
    "id": "650cef06-4954-5d37-a5a5-25b14bb48d5b",
    "name": "Toms River High School North",
    "type": "School",
    "address": "1245 Old Freehold Road, Toms River, NJ 08753-1304",
    "county": "Ocean",
    "source": "nj_schools_public",
    "confidence": "high"
  },
  {
    "id": "1221f7ec-0121-5d20-bbc4-c1363e919c78",
    "name": "Toms River High School South",
    "type": "School",
    "address": "55 Hyers Street, Toms River, NJ 08753",
    "county": "Ocean",
    "source": "nj_schools_public",
    "confidence": "high"
  },
  {
    "id": "cdfc76f5-de08-5925-ad32-4c6ab1e5acd6",
    "name": "Toms River Intermediate School East",
    "type": "School",
    "address": "1519 Hooper Avenue, Toms River, NJ 08753",
    "county": "Ocean",
    "source": "nj_schools_public",
    "confidence": "high"
  },
  {
    "id": "301a57d0-af80-5d9f-ac89-7360c895b56c",
    "name": "Toms River Intermediate School North",
    "type": "School",
    "address": "150 Intermediate North Way, Toms River, NJ 08753",
    "county": "Ocean",
    "source": "nj_schools_public",
    "confidence": "high"
  },
  {
    "id": "ea2df673-813c-5e8d-a925-63b82309034f",
    "name": "Toms River Intermediate School South",
    "type": "School",
    "address": "1675 Pinewald Road, Beachwood, NJ 08722",
    "county": "Ocean",
    "source": "nj_schools_public",
    "confidence": "high"
  },
  {
    "id": "c6ba2fa2-70c3-503a-8f11-c38a4fa8295d",
    "name": "Walnut Street Elementary School",
    "type": "School",
    "address": "60 Walnut Street, Toms River, NJ 08753",
    "county": "Ocean",
    "source": "nj_schools_public",
    "confidence": "high"
  },
  {
    "id": "b4962455-aa2e-5715-a6f5-1f3c94c65bc7",
    "name": "Washington Street Elementary School",
    "type": "School",
    "address": "500 West Earl Court, Toms River, NJ 08753",
    "county": "Ocean",
    "source": "nj_schools_public",
    "confidence": "high"
  },
  {
    "id": "e30bcf54-2165-5b82-ae06-a4c6b59f9008",
    "name": "West Dover Elementary School",
    "type": "School",
    "address": "50 Blue Jay Drive, Toms River, NJ 08753",
    "county": "Ocean",
    "source": "nj_schools_public",
    "confidence": "high"
  },
  {
    "id": "14b0e5ae-7370-5f4c-8d46-9b9bf1d457fd",
    "name": "Tuckerton Elementary School",
    "type": "School",
    "address": "Marine Street, Po Box 217, Tuckerton, NJ 08087",
    "county": "Ocean",
    "source": "nj_schools_public",
    "confidence": "high"
  },
  {
    "id": "8c6d962e-6837-5e78-af5f-3b78fc6ca6b5",
    "name": "Ocean County College",
    "type": "College/University",
    "address": "1 College Drive, Toms River, NJ 08754",
    "county": "Ocean",
    "source": "nj_colleges_curated",
    "confidence": "high"
  },
  {
    "id": "ba39e674-1f12-5f60-a5de-a2d7fbf0d92c",
    "name": "Georgian Court University",
    "type": "College/University",
    "address": "900 Lakewood Avenue, Lakewood, NJ 08701",
    "county": "Ocean",
    "source": "nj_colleges_curated",
    "confidence": "high"
  },
  {
    "id": "649c9187-262a-57f2-a378-1852796507ff",
    "name": "Ocean County Courthouse",
    "type": "Courthouse",
    "address": "118 Washington Street, Toms River, NJ 08753",
    "county": "Ocean",
    "source": "nj_courthouses_curated",
    "confidence": "high"
  },
  {
    "id": "e0e8ac24-dcaf-5588-813a-4c3a49b98457",
    "name": "Barnegat Light Municipal Court",
    "type": "Courthouse",
    "address": "10 West 10th St., Barnegat Light, NJ 08006",
    "county": "Ocean",
    "source": "nj_municipal_courts_official",
    "confidence": "high"
  },
  {
    "id": "5d268269-7a84-5d9e-bc71-0deb6eaa5973",
    "name": "Bay Head Boro Municipal Court",
    "type": "Courthouse",
    "address": "83 Bridge Ave., Bay Head, NJ 08742",
    "county": "Ocean",
    "source": "nj_municipal_courts_official",
    "confidence": "high"
  },
  {
    "id": "3254b106-e2b8-5552-aa7f-60e6d7b19035",
    "name": "Beachwood Municipal Court",
    "type": "Courthouse",
    "address": "1600 Pinewald Rd, Beachwood, NJ 08722",
    "county": "Ocean",
    "source": "nj_municipal_courts_official",
    "confidence": "high"
  },
  {
    "id": "d4e44513-c4dc-5374-b1d1-03e5487612c7",
    "name": "Brick Township Municipal Court",
    "type": "Courthouse",
    "address": "401 Chambers Bridge, Brick, NJ 08723",
    "county": "Ocean",
    "source": "nj_municipal_courts_official",
    "confidence": "high"
  },
  {
    "id": "3d91485a-59b5-5c92-8578-c97a4644bef1",
    "name": "Eagleswood Twp Municipal Court",
    "type": "Courthouse",
    "address": "665 Radio Road, Little Egg Harb, NJ 08087",
    "county": "Ocean",
    "source": "nj_municipal_courts_official",
    "confidence": "high"
  },
  {
    "id": "91fb245d-7155-509d-9833-3ee1e5de3bf2",
    "name": "Island Heights Municipal Court",
    "type": "Courthouse",
    "address": "Po Box 797, Island Heights, NJ 08732",
    "county": "Ocean",
    "source": "nj_municipal_courts_official",
    "confidence": "high"
  },
  {
    "id": "2e989c7d-128a-578e-a9b3-43e079d331d6",
    "name": "Jackson Twp Municipal Court",
    "type": "Courthouse",
    "address": "102 Jackson Drive, Jackson, NJ 08527",
    "county": "Ocean",
    "source": "nj_municipal_courts_official",
    "confidence": "high"
  },
  {
    "id": "4cc04dd2-2613-5f01-be97-07470a7e9aac",
    "name": "Lacey Township Municipal Court",
    "type": "Courthouse",
    "address": "818 West Lacey Road, Forked River, NJ 08731",
    "county": "Ocean",
    "source": "nj_municipal_courts_official",
    "confidence": "high"
  },
  {
    "id": "9a84ea91-b8fc-555d-8a31-b968de9f1a26",
    "name": "Lakehurst Boro Municipal Court",
    "type": "Courthouse",
    "address": "1 Colonial Drive, Manchester, NJ 08759",
    "county": "Ocean",
    "source": "nj_municipal_courts_official",
    "confidence": "high"
  },
  {
    "id": "7258a96e-3541-5ad3-b096-a108df8e93d5",
    "name": "Lakewood Municipal Court",
    "type": "Courthouse",
    "address": "231 Third St, Lakewood, NJ 08701",
    "county": "Ocean",
    "source": "nj_municipal_courts_official",
    "confidence": "high"
  },
  {
    "id": "f3d53130-edb6-51c1-9c57-671b103a5989",
    "name": "Lavallette Municipal Court",
    "type": "Courthouse",
    "address": "1306 Grand Central A, Lavallette, NJ 08735",
    "county": "Ocean",
    "source": "nj_municipal_courts_official",
    "confidence": "high"
  },
  {
    "id": "d9bbf8e7-fec8-554e-987a-20dd07295db7",
    "name": "Long Beach Twp Municipal Court",
    "type": "Courthouse",
    "address": "6805 Long Beach Blvd, Brant Beach, NJ 08008",
    "county": "Ocean",
    "source": "nj_municipal_courts_official",
    "confidence": "high"
  },
  {
    "id": "c26ffc96-dbd2-5bc6-a001-cccc616da03c",
    "name": "Manchester Twp Municipal Court",
    "type": "Courthouse",
    "address": "1 Colonial Drive, Manchester, NJ 08759",
    "county": "Ocean",
    "source": "nj_municipal_courts_official",
    "confidence": "high"
  },
  {
    "id": "1069df9c-e448-5d1e-a8fe-f54a538d884a",
    "name": "Mantoloking Municipal Court",
    "type": "Courthouse",
    "address": "401 Chambers Bridge, Brick, NJ 08723",
    "county": "Ocean",
    "source": "nj_municipal_courts_official",
    "confidence": "high"
  },
  {
    "id": "46bff68f-49b1-5fa8-b2f2-eecae47d0760",
    "name": "Ocean Gate Municipal Court",
    "type": "Courthouse",
    "address": "801 Ocean Gate Ave, Ocean Gate, NJ 08740",
    "county": "Ocean",
    "source": "nj_municipal_courts_official",
    "confidence": "high"
  },
  {
    "id": "12699d38-d1a7-539d-ba91-913cfce25811",
    "name": "Ocean Twp Municipal Court",
    "type": "Courthouse",
    "address": "50 Railroad Avenue, Waretown, NJ 08758",
    "county": "Ocean",
    "source": "nj_municipal_courts_official",
    "confidence": "high"
  },
  {
    "id": "cdbb86c5-4d3d-5eab-bc9b-95ee1fa2413e",
    "name": "Plumsted Twp Municipal Court",
    "type": "Courthouse",
    "address": "1 Colonial Dr, Manchester, NJ 08759",
    "county": "Ocean",
    "source": "nj_municipal_courts_official",
    "confidence": "high"
  },
  {
    "id": "15de5e4b-f6bd-58f2-a9de-25c0892e2fe9",
    "name": "Seaside Hgts Municipal Court",
    "type": "Courthouse",
    "address": "116 Sherman Ave, Seaside Heights, NJ 08751",
    "county": "Ocean",
    "source": "nj_municipal_courts_official",
    "confidence": "high"
  },
  {
    "id": "df1200ec-8a7d-5475-a438-d140ca5c99d2",
    "name": "Seaside Park Boro Municipal Ct",
    "type": "Courthouse",
    "address": "1 Municipal Plaza, Seaside Park, NJ 08752",
    "county": "Ocean",
    "source": "nj_municipal_courts_official",
    "confidence": "high"
  },
  {
    "id": "643b3197-17e0-59a0-856e-5c1c0fbafaf9",
    "name": "Ship Bottom Municipal Court",
    "type": "Courthouse",
    "address": "1621 Long Beach Bl, Ship Bottom, NJ 08008",
    "county": "Ocean",
    "source": "nj_municipal_courts_official",
    "confidence": "high"
  },
  {
    "id": "7a3cbd96-2bc6-50db-acc5-413605b8c2d1",
    "name": "South Toms River Municipal Ct",
    "type": "Courthouse",
    "address": "19 Double Trouble Rd, So Toms River, NJ 08757",
    "county": "Ocean",
    "source": "nj_municipal_courts_official",
    "confidence": "high"
  },
  {
    "id": "d729fc84-0b56-5862-8088-0b47c96fecda",
    "name": "Stafford Township Municipal Ct",
    "type": "Courthouse",
    "address": "260 East Bay Avenue, Manahawkin, NJ 08050",
    "county": "Ocean",
    "source": "nj_municipal_courts_official",
    "confidence": "high"
  },
  {
    "id": "334234f7-b80c-5af5-b1c8-e50c6b3b6c84",
    "name": "Surf City Boro Municipal Court",
    "type": "Courthouse",
    "address": "813 Long Beach Blvd, Surf City, NJ 08008",
    "county": "Ocean",
    "source": "nj_municipal_courts_official",
    "confidence": "high"
  },
  {
    "id": "b9ebe0a5-6071-5ba1-8820-86c9a903c3a5",
    "name": "Toms River Municipal Court",
    "type": "Courthouse",
    "address": "255 Oak Avenue, Toms River, NJ 08753",
    "county": "Ocean",
    "source": "nj_municipal_courts_official",
    "confidence": "high"
  },
  {
    "id": "c3c89753-0d84-5183-8378-db4aafaf0877",
    "name": "Tuckerton Boro Municipal Court",
    "type": "Courthouse",
    "address": "420 E Main St, Tuckerton, NJ 08087",
    "county": "Ocean",
    "source": "nj_municipal_courts_official",
    "confidence": "high"
  },
  {
    "id": "d1582e0e-c98b-5140-82bd-8d35f0b0446c",
    "name": "Ocean County Airport",
    "type": "Airport",
    "address": "101 Airport Road, Bayville, NJ 08721",
    "county": "Ocean",
    "source": "nj_airports_curated",
    "confidence": "high"
  },
  {
    "id": "4fb3de7f-6598-5da6-8c8a-2d675f3d94f6",
    "name": "Bay Head Station",
    "type": "Transit Hub",
    "address": "Main Avenue, Bay Head, NJ 08742",
    "county": "Ocean",
    "source": "nj_transit_hubs_curated",
    "confidence": "high"
  },
  {
    "id": "7d8ded92-dbc2-54d3-afff-755ebab4131f",
    "name": "Ocean County Administration Building",
    "type": "Government Building",
    "address": "101 Hooper Avenue, Toms River, NJ 08753",
    "county": "Ocean",
    "source": "nj_government_buildings_curated",
    "confidence": "high"
  }
]
